empyrical/__init__.py
empyrical/deprecate.py
empyrical/perf_attrib.py
empyrical/periods.py
empyrical/stats.py
empyrical/utils.py
sangreal_ep-0.6.2.dist-info/licenses/LICENSE
sangreal_ep-0.6.2.dist-info/METADATA
sangreal_ep-0.6.2.dist-info/WHEEL
sangreal_ep-0.6.2.dist-info/top_level.txt
sangreal_ep-0.6.2.dist-info/RECORD
