Metadata-Version: 2.4
Name: sangreal-ep
Version: 0.6.2
Summary: sangreal-ep is a Python library with performance and risk statistics commonly used in quantitative finance
Author-email: Quantopian Inc <opensource@quantopian.com>
Maintainer-email: Quantopian Inc <opensource@quantopian.com>
License-Expression: Apache-2.0
Project-URL: Homepage, https://github.com/quantopian/empyrical
Project-URL: Repository, https://github.com/quantopian/empyrical
Project-URL: Documentation, https://quantopian.github.io/empyrical/
Project-URL: Bug Tracker, https://github.com/quantopian/empyrical/issues
Keywords: finance,quantitative,risk,performance,statistics
Classifier: Development Status :: 4 - Beta
Classifier: Programming Language :: Python
Classifier: Programming Language :: Python :: 3
Classifier: Programming Language :: Python :: 3.8
Classifier: Programming Language :: Python :: 3.9
Classifier: Programming Language :: Python :: 3.10
Classifier: Programming Language :: Python :: 3.11
Classifier: Programming Language :: Python :: 3.12
Classifier: Programming Language :: Python :: 3.13
Classifier: Intended Audience :: Science/Research
Classifier: Topic :: Scientific/Engineering
Classifier: Topic :: Scientific/Engineering :: Mathematics
Classifier: Operating System :: OS Independent
Classifier: Programming Language :: Python :: Implementation :: CPython
Requires-Python: >=3.8
License-File: LICENSE
Requires-Dist: numpy>=1.17.0
Requires-Dist: pandas>=0.25.0
Requires-Dist: scipy>=1.3.0
Requires-Dist: six>=1.10
Provides-Extra: dev
Requires-Dist: pytest>=6.0; extra == "dev"
Requires-Dist: pytest-xdist>=2.0; extra == "dev"
Requires-Dist: pytest-cov>=2.10; extra == "dev"
Requires-Dist: flake8; extra == "dev"
Provides-Extra: datareader
Requires-Dist: pandas-datareader>=0.8.0; extra == "datareader"
Provides-Extra: all
Requires-Dist: empyrical[datareader,dev]; extra == "all"
Dynamic: license-file
